just_semantic_search/agent/index_markdown.py
just_semantic_search/agent/rag_agent.py
just_semantic_search/agent/scripts.py
just_semantic_search_agent-0.1.3.dist-info/METADATA
just_semantic_search_agent-0.1.3.dist-info/WHEEL
just_semantic_search_agent-0.1.3.dist-info/entry_points.txt
just_semantic_search_agent-0.1.3.dist-info/RECORD
