Metadata-Version: 2.3
Name: just-semantic-search-agent
Version: 0.1.3
Summary: Semantic and hybrid search agent
License: Apache-2.0
Keywords: python,llm,science,review,hybrid search,semantic search,agent
Author: Anton Kulaga
Author-email: antonkulaga@gmail.com
Requires-Python: >=3.11,<3.15
Classifier: Development Status :: 3 - Alpha
Classifier: Intended Audience :: Developers
Classifier: License :: OSI Approved :: Apache Software License
Classifier: Operating System :: MacOS :: MacOS X
Classifier: Operating System :: Microsoft :: Windows
Classifier: Operating System :: Unix
Classifier: Programming Language :: Python :: 3
Classifier: Programming Language :: Python :: 3.11
Classifier: Programming Language :: Python :: 3.12
Classifier: Programming Language :: Python :: 3.13
Requires-Dist: just-agents-web (>=0.5.6)
Requires-Dist: just-semantic-search-scholar
